bytedance_ui_detection_driver/__init__.py
bytedance_ui_detection_driver-0.0.1.dist-info/METADATA
bytedance_ui_detection_driver-0.0.1.dist-info/WHEEL
bytedance_ui_detection_driver-0.0.1.dist-info/top_level.txt
bytedance_ui_detection_driver-0.0.1.dist-info/RECORD
